LICENSE
MANIFEST.in
README.md
VERSION
setup.py
fieldtrip2mne/__init__.py
fieldtrip2mne/fieldtrip2mne.py
fieldtrip2mne/utils.py
fieldtrip2mne.egg-info/PKG-INFO
fieldtrip2mne.egg-info/SOURCES.txt
fieldtrip2mne.egg-info/dependency_links.txt
fieldtrip2mne.egg-info/requires.txt
fieldtrip2mne.egg-info/top_level.txt