Metadata-Version: 1.1
Name: fieldtrip2mne
Version: 0.0.7
Summary: Convert MEG and EEG brain scan data from FieldTrip toolbox in Matlab to MNE toolbox in python.
Home-page: https://gitlab.com/obob/fieldtrip2mne
Author: Thomas Hartmann & Dirk Gütlin
Author-email: thomas.hartmann@th-ht.de
License: BSD (2 clause)
Keywords: MNE FieldTrip converter MATLAB to Python
Platform: UNKNOWN
Classifier: Development Status :: 4 - Beta
Classifier: License :: OSI Approved :: BSD License
Classifier: Programming Language :: Python :: 2.7
